pyfastani-0.6.1.dist-info/METADATA
pyfastani-0.6.1.dist-info/RECORD
pyfastani-0.6.1.dist-info/WHEEL
pyfastani-0.6.1.dist-info/licenses/COPYING
pyfastani/_patch.pxi
pyfastani/_utils.hpp
pyfastani/_atomic_vector.hpp
pyfastani/py.typed
pyfastani/__init__.py
pyfastani/_utils.pxd
pyfastani/_fastani.pypy38-pp73-x86_64-linux-gnu.so
pyfastani/_fasta.pyx
pyfastani/_fasta.pypy38-pp73-x86_64-linux-gnu.so
pyfastani/_version.py
pyfastani/_atomic_vector.pxd
pyfastani/_fastani.pyi
pyfastani/_utils.cpp
pyfastani/CMakeLists.txt
pyfastani/_fastani.pyx
pyfastani/tests/test_sketch.py
pyfastani/tests/__init__.py
pyfastani/tests/test_ani.py
pyfastani/tests/requirements.txt
pyfastani/tests/data/BGC0001428.faa
pyfastani/tests/data/__init__.py
pyfastani/tests/data/BGC0001425.faa
pyfastani/tests/data/BGC0001427.faa
pyfastani/_sequtils/complement.h
pyfastani/_sequtils/ssse3.c
pyfastani/_sequtils/sequtils.cpp
pyfastani/_sequtils/__init__.pxd
pyfastani/_sequtils/neon.c
pyfastani/_sequtils/sse2.c
pyfastani/_sequtils/sequtils.h
pyfastani/_sequtils/CMakeLists.txt
