Metadata-Version: 2.1
Name: pyfastani
Version: 0.6.1
Summary: Cython bindings and Python interface to FastANI, a method for fast whole-genome similarity estimation.
Keywords: bioinformatics,genomics,average,nucleotide,identity
Author-Email: Martin Larralde <martin.larralde@embl.de>
License: MIT License
Classifier: Development Status :: 4 - Beta
Classifier: Intended Audience :: Developers
Classifier: Intended Audience :: Science/Research
Classifier: License :: OSI Approved :: MIT License
Classifier: Operating System :: OS Independent
Classifier: Programming Language :: C++
Classifier: Programming Language :: Cython
Classifier: Programming Language :: Python :: 3.7
Classifier: Programming Language :: Python :: 3.8
Classifier: Programming Language :: Python :: 3.9
Classifier: Programming Language :: Python :: 3.10
Classifier: Programming Language :: Python :: 3.11
Classifier: Programming Language :: Python :: 3.12
Classifier: Programming Language :: Python :: 3.13
Classifier: Programming Language :: Python :: Implementation :: CPython
Classifier: Programming Language :: Python :: Implementation :: PyPy
Classifier: Topic :: Scientific/Engineering :: Bio-Informatics
Classifier: Topic :: Scientific/Engineering :: Medical Science Apps.
Classifier: Typing :: Typed
Project-URL: Documentation, https://pyfastani.readthedocs.io/en/stable/
Project-URL: Bug tracker, https://github.com/althonos/pyfastani/issues
Project-URL: Changelog, https://github.com/althonos/pyfastani/blob/main/CHANGELOG.md
Project-URL: Coverage, https://codecov.io/gh/althonos/pyfastani/
Project-URL: Builds, https://github.com/althonos/pyfastani/actions
Project-URL: Pypi, https://pypi.org/project/pyfastani
Project-URL: Piwheels, https://www.piwheels.org/project/pyfastani/
Requires-Python: >=3.7
